fpds/__init__.py
fpds/config.py
fpds/errors.py
fpds/cli/__init__.py
fpds/cli/parse.py
fpds/constants/__init__.py
fpds/constants/fields.json
fpds/core/__init__.py
fpds/core/mixins.py
fpds/core/parser.py
fpds/core/xml.py
fpds/utilities/__init__.py
fpds/utilities/decorators.py
fpds/utilities/params.py
fpds-1.4.2.dist-info/licenses/LICENSE
fpds-1.4.2.dist-info/METADATA
fpds-1.4.2.dist-info/WHEEL
fpds-1.4.2.dist-info/entry_points.txt
fpds-1.4.2.dist-info/top_level.txt
fpds-1.4.2.dist-info/RECORD
