Metadata-Version: 2.4
Name: fpds
Version: 1.4.2
Summary: A parser for the Federal Procurement Data System (FPDS) Atom feed
Author-email: Derek Herincx <derek663@gmail.com>
License: The MIT License
Project-URL: Repository, https://github.com/dherincx92/fpds
Project-URL: Issues, https://github.com/dherincx92/fpds/issues
Keywords: fpds,python,atom feed,cli,xml
Classifier: Intended Audience :: Developers
Classifier: Natural Language :: English
Classifier: Programming Language :: Python :: 3.11
Classifier: Programming Language :: Python :: 3.12
Classifier: Programming Language :: Python :: 3.13
Requires-Python: >=3.11
License-File: LICENSE
Requires-Dist: aiohttp<4.0.0,>=3.9.2
Requires-Dist: click<9.0.0,>=8.1.3
Requires-Dist: tqdm<5.0.0,>=4.67.1
Provides-Extra: dev
Requires-Dist: ipdb==0.13.9; extra == "dev"
Requires-Dist: ipython==8.5.0; extra == "dev"
Requires-Dist: ruff==0.12.1; extra == "dev"
Requires-Dist: mypy>=0.910; extra == "dev"
Requires-Dist: types-tqdm==4.64.7.9; extra == "dev"
Requires-Dist: versioningit<4.0.0,>=3.0.0; extra == "dev"
Provides-Extra: tests
Requires-Dist: pytest==7.1.3; extra == "tests"
Requires-Dist: pytest-cov==3.0.0; extra == "tests"
Requires-Dist: pytest-runner==6.0.0; extra == "tests"
Provides-Extra: packaging
Requires-Dist: build==0.8.0; extra == "packaging"
Requires-Dist: wheel==0.37.1; extra == "packaging"
Requires-Dist: twine==5.1.1; extra == "packaging"
Provides-Extra: all
Requires-Dist: fpds[dev]; extra == "all"
Requires-Dist: fpds[tests]; extra == "all"
Requires-Dist: fpds[packaging]; extra == "all"
Dynamic: license-file
